LICENSE
MANIFEST.in
README.md
rpm-s3
setup.py
version.txt
rpm_s3/__init__.py
rpm_s3/empty-repo/repodata/401dc19bda88c82c403423fb835844d64345f7e95f5b9835888189c03834cc93-filelists.xml.gz
rpm_s3/empty-repo/repodata/6bf9672d0862e8ef8b8ff05a2fd0208a922b1f5978e6589d87944c88259cb670-other.xml.gz
rpm_s3/empty-repo/repodata/77a287c136f4ff47df506229b9ba67d57273aa525f06ddf41a3fef39908d61a7-other.sqlite.bz2
rpm_s3/empty-repo/repodata/8596812757300b1d87f2682aff7d323fdeb5dd8ee28c11009e5980cb5cd4be14-primary.sqlite.bz2
rpm_s3/empty-repo/repodata/dabe2ce5481d23de1f4f52bdcfee0f9af98316c9e0de2ce8123adeefa0dd08b9-primary.xml.gz
rpm_s3/empty-repo/repodata/f8606d9f21d61a8bf405af7144e16f6d7cb1202becb78ba5fea7d0f1cd06a0b2-filelists.sqlite.bz2
rpm_s3/empty-repo/repodata/repomd.xml
rpm_s3/vendor/__init__.py
rpm_s3/vendor/createrepo/.gitignore
rpm_s3/vendor/createrepo/AUTHORS
rpm_s3/vendor/createrepo/COPYING
rpm_s3/vendor/createrepo/COPYING.lib
rpm_s3/vendor/createrepo/ChangeLog
rpm_s3/vendor/createrepo/Makefile
rpm_s3/vendor/createrepo/README
rpm_s3/vendor/createrepo/__init__.py
rpm_s3/vendor/createrepo/createrepo.bash
rpm_s3/vendor/createrepo/createrepo.spec
rpm_s3/vendor/createrepo/dmd.py
rpm_s3/vendor/createrepo/genpkgmetadata.py
rpm_s3/vendor/createrepo/mergerepo.py
rpm_s3/vendor/createrepo/modifyrepo.py
rpm_s3/vendor/createrepo/worker.py
rpm_s3/vendor/createrepo/bin/Makefile
rpm_s3/vendor/createrepo/bin/createrepo
rpm_s3/vendor/createrepo/bin/mergerepo
rpm_s3/vendor/createrepo/bin/modifyrepo
rpm_s3/vendor/createrepo/createrepo/Makefile
rpm_s3/vendor/createrepo/createrepo/__init__.py
rpm_s3/vendor/createrepo/createrepo/deltarpms.py
rpm_s3/vendor/createrepo/createrepo/merge.py
rpm_s3/vendor/createrepo/createrepo/readMetadata.py
rpm_s3/vendor/createrepo/createrepo/utils.py
rpm_s3/vendor/createrepo/createrepo/yumbased.py
rpm_s3/vendor/createrepo/docs/Makefile
rpm_s3/vendor/createrepo/docs/createrepo.8
rpm_s3/vendor/createrepo/docs/mergerepo.1
rpm_s3/vendor/createrepo/docs/modifyrepo.1
sts_rpm_s3.egg-info/PKG-INFO
sts_rpm_s3.egg-info/SOURCES.txt
sts_rpm_s3.egg-info/dependency_links.txt
sts_rpm_s3.egg-info/requires.txt
sts_rpm_s3.egg-info/top_level.txt